__init__.py
easy_monnify.py
easy_monnify-1.0.2.dist-info/LICENSE
easy_monnify-1.0.2.dist-info/METADATA
easy_monnify-1.0.2.dist-info/WHEEL
easy_monnify-1.0.2.dist-info/top_level.txt
easy_monnify-1.0.2.dist-info/RECORD
