Metadata-Version: 2.1
Name: easy_monnify
Version: 1.0.2
Summary: A python library to seamlessly integrate Monnify payment gateway into your projects
Author-email: Rigan Tech <rigantech@gmail.com>
License: MIT
Project-URL: homepage, https://github.com/Rigantech/easy_monnify
Project-URL: repository, https://github.com/Rigantech/easy_monnify
Project-URL: Issues, https://github.com/Rigantech/easy_monnify/issues
Classifier: Programming Language :: Python :: 3
Classifier: License :: OSI Approved :: MIT License
Classifier: Operating System :: OS Independent
Requires-Python: >=3.8
License-File: LICENSE
Requires-Dist: requests>=2.25.0
